jtv/__init__.py
jtv/app.py
jtv/cli.py
jtv/jsontree.py
jtv/template.py
jtv/themes.py
jtv-1.74.0.dist-info/LICENSE
jtv-1.74.0.dist-info/METADATA
jtv-1.74.0.dist-info/WHEEL
jtv-1.74.0.dist-info/entry_points.txt
jtv-1.74.0.dist-info/top_level.txt
jtv-1.74.0.dist-info/zip-safe
jtv-1.74.0.dist-info/RECORD
