Metadata-Version: 2.1
Name: jtv
Version: 1.74.0
Summary: Command line utility for visualising JSON and YAML schemas as text trees
Home-page: https://github.com/astrocyte-medical/jtv
Author: Astrocyte Medical LTD
Author-email: Astrocyte Medical LTD <info@astrocyte-medical.com>
License: MIT License        
Project-URL: Homepage, https://github.com/astrocyte-medical/jtv
Keywords: json,tree,viewer,cli
Platform: Linux
Classifier: License :: OSI Approved :: MIT License
Classifier: Programming Language :: Python :: 3
Requires-Python: >=3.9
License-File: LICENSE
Requires-Dist: click
Requires-Dist: PyYAML (>5.1)
Requires-Dist: colr (==0.9.1)
Requires-Dist: asciitree
Provides-Extra: dev
Requires-Dist: black ; extra == 'dev'
Requires-Dist: bumpver ; extra == 'dev'
Requires-Dist: isort ; extra == 'dev'
Requires-Dist: pip-tools ; extra == 'dev'
Requires-Dist: pytest ; extra == 'dev'
